[{
        "id": 1,
        "player1": "bail",
        "player2": "trinh",
        "player1Score": 500,
        "player2Score": 300,
        "isComplete": false,
        "winner": null
    },
    {
        "id": 2,
        "player1": "admin",
        "player2": "bail",
        "player1Score": 200,
        "player1Difficulty": "MED",
        "player1AnswerHistory": [true, false, true],
        "player2Score": 400,
        "player2Difficulty": "MED",
        "playe2AnswerHistory": [false, false, false],
        "selectedCategories": [
            "Algorithms",
            "Web Development",
            "Artificial Intelligence",
            "Databases",
            "Programming Languages"
        ],
        "completedQuestionIds": [1, 7, 3, 2],
        "isComplete": false,
        "winner": null
    }
]